modern_captcha/__init__.py
modern_captcha/backends.py
modern_captcha/forms.py
modern_captcha/models.py
modern_captcha/utils.py
modern_captcha/views.py
django_modern_captcha-0.1.2.dist-info/METADATA
django_modern_captcha-0.1.2.dist-info/WHEEL
django_modern_captcha-0.1.2.dist-info/top_level.txt
django_modern_captcha-0.1.2.dist-info/RECORD
