Metadata-Version: 2.1
Name: django-modern-captcha
Version: 0.1.2
Summary: A modern CAPTCHA solution for Django with behavioral analysis
Home-page: https://github.com/manish-codefyn/django-modern-captcha
Author: Manish Sharma
Author-email: manis.shr@gmail.com
License: UNKNOWN
Platform: UNKNOWN
Classifier: Framework :: Django
Classifier: Programming Language :: Python :: 3
Classifier: License :: OSI Approved :: MIT License
Requires-Python: >=3.6
Requires-Dist: Django>=3.2
Requires-Dist: numpy
Requires-Dist: scikit-learn
